llama_index/packs/recursive_retriever/__init__.py
llama_index/packs/recursive_retriever/embedded_tables_unstructured/__init__.py
llama_index/packs/recursive_retriever/embedded_tables_unstructured/base.py
llama_index/packs/recursive_retriever/small_to_big/__init__.py
llama_index/packs/recursive_retriever/small_to_big/base.py
llama_index_packs_recursive_retriever-0.7.1.dist-info/METADATA
llama_index_packs_recursive_retriever-0.7.1.dist-info/WHEEL
llama_index_packs_recursive_retriever-0.7.1.dist-info/licenses/LICENSE
llama_index_packs_recursive_retriever-0.7.1.dist-info/RECORD
