Metadata-Version: 2.4
Name: llama-index-packs-recursive-retriever
Version: 0.7.1
Summary: llama-index packs recursive_retriever integration
Author-email: Your Name <you@example.com>
Maintainer: jerryjliu
License-Expression: MIT
License-File: LICENSE
Keywords: big,embedded,recursive,retriever,small,tables,unstructured
Requires-Python: <4.0,>=3.9
Requires-Dist: llama-index-core<0.15,>=0.13.0
Requires-Dist: llama-index-llms-openai<0.6,>=0.5.0
Requires-Dist: llama-index-readers-file<0.6,>=0.5.0
Requires-Dist: lxml<6,>=5.1.0
Requires-Dist: unstructured<0.15,>=0.14.3
